[
  {
    "id": "doc-f55297895614-c0000",
    "index": 0,
    "text": "Szoftverfejleszt\u00e9s alapjai\nEls\u0151 ZH dolgozat\nAzonos\u00edt\u00f3: M\nA feladat megold\u00e1s\u00e1ra \u00e9s beny\u00fajt\u00e1s\u00e1ra 120 perc \u00e1ll rendelkez\u00e9sre. A l\u00e9trehozott projekt megnevez\u00e9se tartalmazza az \u00d6n nev\u00e9t (\u00e9kezetek\nn\u00e9lk\u00fcl), Neptun k\u00f3dj\u00e1t \u00e9s a dolgozat azonos\u00edt\u00f3j\u00e1t (pl. AliceBob_ABC123_M). A megold\u00e1s\u00e1t tartalmaz\u00f3 mapp\u00e1t (a teljes solution-t) t\u00f6m\u00f6r\u00edtve,\na http://zh.nik.lan c\u00edmen el\u00e9rhet\u0151 fel\u00fcleten kereszt\u00fcl ny\u00fajtsa be.\n\u00dcgyeljen a ford\u00edt\u00e1si hib\u00e1t\u00f3l mentes k\u00f3dra, ellenkez\u0151 esetben a megold\u00e1s nem \u00e9rt\u00e9kelhet\u0151.\nK\u00e9sz\u00edtsen konzolos alkalmaz\u00e1st egy csomagsz\u00e1ll\u00edt\u00f3 szolg\u00e1lat sz\u00e1m\u00e1ra a csomagjaik nyomon k\u00f6vet\u00e9s\u00e9re.\nA teljes \u00e9rt\u00e9k\u0171 megold\u00e1shoz elv\u00e1r\u00e1s a kurzuson t\u00e1rgyalt m\u00f3dszerek \u00e9s technik\u00e1k alkalmaz\u00e1sa.\n1\nHozza l\u00e9tre az IDeliverable interf\u00e9szt.\nEgy k\u00e9zbes\u00edtend\u0151 k\u00fcldem\u00e9ny eset\u00e9n ismert annak\ngrammban adott t\u00f6mege (Weight, eg\u00e9sz \u00e9rt\u00e9k) \u00e9s a k\u00e9zbes\u00edt\u00e9si c\u00edme (Address, karakterl\u00e1nc),\nvalamint az objektum rendelkezik \u00e1ll egy double CalculatePrice(bool fromLocker) szignat\u00far\u00e1j\u00fa\nmet\u00f3dussal, amely a csomagsz\u00e1ll\u00edt\u00e1si d\u00edjat sz\u00e1molja ki.\n(2 pont)\n2\nK\u00e9sz\u00edtsen egy Envelope nev\u0171 oszt\u00e1lyt, amely megval\u00f3s\u00edtja az IDeliverable interf\u00e9szt.\nAz\noszt\u00e1ly egy lapos form\u00e1tum\u00fa k\u00fcldem\u00e9nyt (pl. bor\u00edt\u00e9kot, hanglemezt) reprezent\u00e1l.\n(8 pont)\n\u2022 A k\u00fcldem\u00e9ny le\u00edr\u00e1s\u00e1t t\u00e1rolja egy karakterl\u00e1nc t\u00edpus\u00fa mez\u0151ben.\n\u2022 A t\u00f6meg, c\u00edmzett \u00e9s a le\u00edr\u00e1s a konstruktor param\u00e9terek\u00e9nt adhat\u00f3 meg.\n\u2022 A sz\u00e1ll\u00edt\u00e1si d\u00edj 50 grammig 200 Ft, 51\u2013500 gramm k\u00f6z\u00f6tt 400 Ft, 501\u20132000 gramm k\u00f6z\u00f6tt 1000\nFt, f\u00fcggetlen\u00fcl att\u00f3l, hogy automat\u00e1b\u00f3l t\u00f6rt\u00e9nt-e a felad\u00e1s (fromLocker param\u00e9ter).\n\u2022 A d\u00edjsz\u00e1m\u00edt\u00e1s sor\u00e1n dobjon el OverweightException kiv\u00e9telt, ha a k\u00fcldem\u00e9ny t\u00f6mege\nmeghaladja a 2000 grammot. K\u00e9sz\u00edtse el az eml\u00edtett kiv\u00e9tel oszt\u00e1lyt is.\n\u2022 A ToString met\u00f3dus adja vissza a csomag adatait az al\u00e1bbi form\u00e1tumnak megfelel\u0151en.\nC\u00edmzett:\nTravis Kelce / Le\u00edr\u00e1s:\nTaylor Swift hanglemez / T\u00f6meg:750 g\n3\nK\u00e9sz\u00edtsen egy Parcel nev\u0171 absztrakt oszt\u00e1lyt, amely megval\u00f3s\u00edtja az IDeliverable \u00e9s az",
    "char_count": 1906,
    "token_estimate": 476
  },
  {
    "id": "doc-f55297895614-c0001",
    "index": 1,
    "text": "mege\nmeghaladja a 2000 grammot. K\u00e9sz\u00edtse el az eml\u00edtett kiv\u00e9tel oszt\u00e1lyt is.\n\u2022 A ToString met\u00f3dus adja vissza a csomag adatait az al\u00e1bbi form\u00e1tumnak megfelel\u0151en.\nC\u00edmzett:\nTravis Kelce / Le\u00edr\u00e1s:\nTaylor Swift hanglemez / T\u00f6meg:750 g\n3\nK\u00e9sz\u00edtsen egy Parcel nev\u0171 absztrakt oszt\u00e1lyt, amely megval\u00f3s\u00edtja az IDeliverable \u00e9s az\nmege\nmeghaladja a 2000 grammot. K\u00e9sz\u00edtse el az eml\u00edtett kiv\u00e9tel oszt\u00e1lyt is.\n\u2022 A ToString met\u00f3dus adja vissza a csomag adatait az al\u00e1bbi form\u00e1tumnak megfelel\u0151en.\nC\u00edmzett:\nTravis Kelce / Le\u00edr\u00e1s:\nTaylor Swift hanglemez / T\u00f6meg:750 g\n3\nK\u00e9sz\u00edtsen egy Parcel nev\u0171 absztrakt oszt\u00e1lyt, amely megval\u00f3s\u00edtja az IDeliverable \u00e9s az\nIComparable interf\u00e9szeket. Az oszt\u00e1ly egy csomagot reprezent\u00e1l. Az \u00f6sszehasonl\u00edt\u00e1s t\u00f6rt\u00e9njen a\nk\u00fcldem\u00e9ny t\u00f6mege alapj\u00e1n.\n(8 pont)\n\u2022 T\u00e1rolja\na\ncsomag\nelhelyez\u00e9s\u00e9nek\nm\u00f3dj\u00e1t,\namely\nlegyen\nlek\u00e9rdezhet\u0151\negy\npublikus\ntulajdons\u00e1gon kereszt\u00fcl. Az elhelyez\u00e9si m\u00f3d (tetsz\u0151leges, \u00e1ll\u00edtva, fektetve) az al\u00e1bbiak egyike\nlehet: Arbitrary, Horizontal, Vertical. (Ehhez k\u00e9sz\u00edtse el a megfelel\u0151 enumot is.)\n\u2022 A t\u00f6meg, c\u00edmzett \u00e9s az elhelyez\u00e9si m\u00f3d a konstruktor param\u00e9terek\u00e9nt adhat\u00f3 meg. K\u00e9sz\u00edtsen\negy olyan konstruktort is, amely csak a t\u00f6meget \u00e9s a c\u00edmzettet fogadja.\n\u2022 A CalculatePrice met\u00f3dus legyen absztrakt.\n\u2022 A ToString met\u00f3dus adja vissza a csomag adatait az Envelope-n\u00e1l megadott form\u00e1tumhoz\nhasonl\u00f3an.\n4\nK\u00e9sz\u00edtsen egy NormalParcel nev\u0171 oszt\u00e1lyt, amely a Parcel oszt\u00e1lyb\u00f3l sz\u00e1rmazik. Az oszt\u00e1ly\negy hagyom\u00e1nyos csomagot reprezent\u00e1l.\n(6 pont)\n\u2022 A t\u00f6meg \u00e9s a c\u00edmzett a konstruktor param\u00e9terek\u00e9nt adhat\u00f3 meg.\n\u2022 A csomag elhelyez\u00e9s\u00e9nek m\u00f3dj\u00e1t p\u00e9ld\u00e1nyos\u00edt\u00e1skor v\u00e9letlenszer\u0171en \u00e1ll\u00edtsa be.\n\u2022 A sz\u00e1ll\u00edt\u00e1s alapd\u00edja 500 Ft + grammonk\u00e9nt 1 Ft. Ha a csomagot automat\u00e1b\u00f3l adj\u00e1k fel, akkor\nvonjon le a d\u00edjb\u00f3l 250 Ft-ot.\n1",
    "char_count": 1742,
    "token_estimate": 435
  },
  {
    "id": "doc-f55297895614-c0002",
    "index": 2,
    "text": "t\u00e1ly\negy hagyom\u00e1nyos csomagot reprezent\u00e1l.\n(6 pont)\n\u2022 A t\u00f6meg \u00e9s a c\u00edmzett a konstruktor param\u00e9terek\u00e9nt adhat\u00f3 meg.\n\u2022 A csomag elhelyez\u00e9s\u00e9nek m\u00f3dj\u00e1t p\u00e9ld\u00e1nyos\u00edt\u00e1skor v\u00e9letlenszer\u0171en \u00e1ll\u00edtsa be.\n\u2022 A sz\u00e1ll\u00edt\u00e1s alapd\u00edja 500 Ft + grammonk\u00e9nt 1 Ft. Ha a csomagot automat\u00e1b\u00f3l adj\u00e1k fel, akkor\nvonjon le a d\u00edjb\u00f3l 250 Ft-ot.\n1\n\nSzoftverfejleszt\u00e9s alapjai\nEls\u0151 ZH dolgozat\nAzonos\u00edt\u00f3: M\n5\nK\u00e9sz\u00edtsen egy FragileParcel nev\u0171 oszt\u00e1lyt, amely a Parcel oszt\u00e1lyb\u00f3l sz\u00e1rmazik. Az oszt\u00e1ly\negy t\u00f6r\u00e9keny csomagot reprezent\u00e1l.\n(6 pont)\n\u2022 A sz\u00e1ll\u00edt\u00e1s alapd\u00edja 1000 Ft + grammonk\u00e9nt 2 Ft. A csomag nem adhat\u00f3 fel automat\u00e1b\u00f3l, ha\nm\u00e9gis ez t\u00f6rt\u00e9nne, dobjon DeliveryException-t, amelynek hiba\u00fczenet\u00e9ben legyen t\u00e1j\u00e9koztat\u00f3\n\u00fczenet a hiba ok\u00e1r\u00f3l.\n\u2022 A t\u00f6meg, a c\u00edmzett \u00e9s az elhelyez\u00e9si m\u00f3d a konstruktor param\u00e9terek\u00e9nt adhat\u00f3 meg. Dobjon\nIncorrectOrientationException-t, ha a csomag elhelyez\u00e9si m\u00f3dja Arbitrary volna. Hozza\nl\u00e9tre ezt a kiv\u00e9teloszt\u00e1lyt a DeliveryException lesz\u00e1rmazottjak\u00e9nt.\nAz eldobott kiv\u00e9tel\nobjektum tartalmazzon referenci\u00e1t az \u00e9ritett csomagra.\n6\nEgy fut\u00e1rt a Courier nev\u0171 oszt\u00e1ly egy p\u00e9ld\u00e1nya reprezent\u00e1lja.\nHozza l\u00e9tre az oszt\u00e1lyt az\nal\u00e1bbiak szerint.\n(8 pont)\n\u2022 A k\u00e9zbes\u00edtend\u0151 k\u00fcldem\u00e9nyeket (a fentiek b\u00e1rmelyike) t\u00e1rolja egy t\u00f6mbben, azok aktu\u00e1lis\n\u00f6sszt\u00f6meg\u00e9t pedig egy mez\u0151ben, amely publikus tulajdons\u00e1gon kereszt\u00fcl lek\u00e9rdezhet\u0151.\n\u2022 A t\u00f6mb elemsz\u00e1m\u00e1t a konstruktorb\u00f3l lehessen be\u00e1ll\u00edtani.\n\u2022 Rendelkezzen egy void PickUpItem(IDeliverable item) szignat\u00far\u00e1j\u00fa publikus met\u00f3dussal, amely\na param\u00e9terk\u00e9nt kapott k\u00fclem\u00e9nyt elhelyezi a k\u00e9zbes\u00edtend\u0151 elemeket tartalmaz\u00f3 t\u00f6mbben. Ha\nm\u00e1r nincsen t\u00f6bb szabad hely, jelezze egy DeliveryException kiv\u00e9tel eldob\u00e1s\u00e1val.\n\u2022 Rendelkezzen egy IDeliverable[] FragilesSorted() nev\u0171 met\u00f3dussal, amely egy kimeneti t\u00f6mbbe\nv\u00e1logatja a FragileParcel t\u00edpus\u00fa k\u00fcldem\u00e9nyeket.\nA met\u00f3dus a kiv\u00e1logatott elemeket\nn\u00f6vekv\u0151en rendezett sorrendben adja vissza.\n7\nA megismertek szerint k\u00e9sz\u00edtsen egys\u00e9gteszteket az al\u00e1bbiak ellen\u0151rz\u00e9s\u00e9re.\n(12 pont)\n\u2022 Envelope oszt\u00e1ly m\u0171k\u00f6d\u00e9se\n\u2013 helyesen kalkul\u00e1lt csomagsz\u00e1ll\u00edt\u00e1si d\u00edj automat\u00e1b\u00f3l \u00e9s nem automat\u00e1b\u00f3l feladva\n\u2013 2000 g-n\u00e1l nehezebb k\u00fcldem\u00e9ny eset\u00e9n el\u0151\u00e1ll a megfelel\u0151 kiv\u00e9ltel\n\u2022 FragileParcel oszt\u00e1ly m\u0171k\u00f6d\u00e9se\n\u2013 csomagautomat\u00e1s d\u00edj kalkul\u00e1ci\u00f3n\u00e1l el\u0151\u00e1ll a megfelel\u0151 kiv\u00e9ltel",
    "char_count": 2230,
    "token_estimate": 557
  },
  {
    "id": "doc-f55297895614-c0003",
    "index": 3,
    "text": "teszteket az al\u00e1bbiak ellen\u0151rz\u00e9s\u00e9re.\n(12 pont)\n\u2022 Envelope oszt\u00e1ly m\u0171k\u00f6d\u00e9se\n\u2013 helyesen kalkul\u00e1lt csomagsz\u00e1ll\u00edt\u00e1si d\u00edj automat\u00e1b\u00f3l \u00e9s nem automat\u00e1b\u00f3l feladva\n\u2013 2000 g-n\u00e1l nehezebb k\u00fcldem\u00e9ny eset\u00e9n el\u0151\u00e1ll a megfelel\u0151 kiv\u00e9ltel\n\u2022 FragileParcel oszt\u00e1ly m\u0171k\u00f6d\u00e9se\n\u2013 csomagautomat\u00e1s d\u00edj kalkul\u00e1ci\u00f3n\u00e1l el\u0151\u00e1ll a megfelel\u0151 kiv\u00e9ltel\nteszteket az al\u00e1bbiak ellen\u0151rz\u00e9s\u00e9re.\n(12 pont)\n\u2022 Envelope oszt\u00e1ly m\u0171k\u00f6d\u00e9se\n\u2013 helyesen kalkul\u00e1lt csomagsz\u00e1ll\u00edt\u00e1si d\u00edj automat\u00e1b\u00f3l \u00e9s nem automat\u00e1b\u00f3l feladva\n\u2013 2000 g-n\u00e1l nehezebb k\u00fcldem\u00e9ny eset\u00e9n el\u0151\u00e1ll a megfelel\u0151 kiv\u00e9ltel\n\u2022 FragileParcel oszt\u00e1ly m\u0171k\u00f6d\u00e9se\n\u2013 csomagautomat\u00e1s d\u00edj kalkul\u00e1ci\u00f3n\u00e1l el\u0151\u00e1ll a megfelel\u0151 kiv\u00e9ltel\n\u2013 hib\u00e1s elhelyez\u00e9si m\u00f3d be\u00e1ll\u00edt\u00e1sakor el\u0151\u00e1ll a megfelel\u0151 kiv\u00e9tel\n\u2022 Courier oszt\u00e1ly m\u0171k\u00f6d\u00e9se\n\u2013 a PickUpItem megh\u00edv\u00e1sakor az \u00f6sszt\u00f6meg helyesen \u00e9rt\u00e9kre \u00e1ll be\n\u2013 a FragilesSorted helyesen elv\u00e9gzi a kiv\u00e1logat\u00e1st \u00e9s a rendez\u00e9st\n2",
    "char_count": 864,
    "token_estimate": 216
  }
]