[
  {
    "id": "doc-d4c67f4885a3-c0000",
    "index": 0,
    "text": "Vizsgajegyzet: Line\u00e1ris Regresszi\u00f3 Egytv\u00e1ltoz\u00f3s\nEsetben\nML-005 Lecture 2 | Stanford University | Andrew Ng\n2025. j\u00fanius 14., 15:52 CEST\nForr\u00e1s\nDiasor (\u201eline\u00e1risregresszi\u00f3 1.pptx\u201d) \u00e9s PDF (\u201eline\u00e1ris regresszi\u00f3.pdf\u201d)\n1. Bevezet\u00e9s\nA line\u00e1ris regresszi\u00f3 egy fel\u00fcgyelt tanul\u00e1si m\u00f3dszer, amelynek c\u00e9lja egy folytonos kimeneti\nv\u00e1ltoz\u00f3 (y) elrejelz\u00e9se egy vagy t\u00f6bb bemeneti v\u00e1ltoz\u00f3 (x) alapj\u00e1n. Az egytv\u00e1ltoz\u00f3s line-\n\u00e1ris regresszi\u00f3 eset\u00e9ben egyetlen bemenetet haszn\u00e1lunk, amely egy egyszer, de hat\u00e9kony\nmegk\u00f6zel\u00edt\u00e9s a g\u00e9pi tanul\u00e1sban.\n\u2022 Regresszi\u00f3 de\ufb01n\u00edci\u00f3ja: A regresszi\u00f3 megbecs\u00fcli a kapcsolatot a f\u00fcgg v\u00e1ltoz\u00f3 (y,\namit elre akarunk jelezni) \u00e9s egy f\u00fcggetlen v\u00e1ltoz\u00f3 (x, magyar\u00e1z\u00f3 v\u00e1ltoz\u00f3) k\u00f6z\u00f6tt.\nA modell param\u00e9terei le\u00edrj\u00e1k, hogyan befoly\u00e1solja x az y-t, \u00edgy seg\u00edtve az adatok\nk\u00f6z\u00f6tti \u00f6sszef\u00fcgg\u00e9sek meg\u00e9rt\u00e9s\u00e9t \u00e9s elrejelz\u00e9s\u00e9t.\n\u2022 C\u00e9l: Folytonos \u00e9rt\u00e9k kimenet (y) elrejelz\u00e9se egy bemenet (x) alapj\u00e1n, p\u00e9ld\u00e1ul egy\nval\u00f3s sz\u00e1m predikci\u00f3ja minden mintapontra.\n\u2022 P\u00e9ld\u00e1k:\n\u2013 H\u00e1z\u00e1rak elrejelz\u00e9se a h\u00e1z m\u00e9rete alapj\u00e1n (pl. Portland, OR adathalmaz).\n\u2013 C\u00e9g pro\ufb01tj\u00e1nak becsl\u00e9se az \u00fcgyfelek sz\u00e1ma alapj\u00e1n.\n\u2022 Tanul\u00e1si t\u00edpus: Fel\u00fcgyelt tanul\u00e1s, c\u00edmk\u00e9zett adatokkal: (x(i), y(i)), ahol minden\nadatpont egy bemenet-kimenet p\u00e1rt tartalmaz.\n\u2022 Kontextus: Egytv\u00e1ltoz\u00f3s line\u00e1ris regresszi\u00f3, ahol csak egy bemenet (x) van, \u00e9s a\nc\u00e9l egy line\u00e1ris kapcsolat modellez\u00e9se.\n2. Modell Reprezent\u00e1ci\u00f3\nAz egytv\u00e1ltoz\u00f3s line\u00e1ris regresszi\u00f3 c\u00e9lja egy line\u00e1ris f\u00fcggv\u00e9ny illeszt\u00e9se az adatokra, amely\na bemenet (x) alapj\u00e1n elrejelzi a kimenetet (y). Ez a folyamat egy tanul\u00f3 algoritmus\nseg\u00edts\u00e9g\u00e9vel t\u00f6rt\u00e9nik, amely a tan\u00edt\u00f3 adatok alapj\u00e1n meghat\u00e1rozza a modell param\u00e9tereit.\n1",
    "char_count": 1635,
    "token_estimate": 408
  },
  {
    "id": "doc-d4c67f4885a3-c0001",
    "index": 1,
    "text": "s kapcsolat modellez\u00e9se.\n2. Modell Reprezent\u00e1ci\u00f3\nAz egytv\u00e1ltoz\u00f3s line\u00e1ris regresszi\u00f3 c\u00e9lja egy line\u00e1ris f\u00fcggv\u00e9ny illeszt\u00e9se az adatokra, amely\na bemenet (x) alapj\u00e1n elrejelzi a kimenetet (y). Ez a folyamat egy tanul\u00f3 algoritmus\nseg\u00edts\u00e9g\u00e9vel t\u00f6rt\u00e9nik, amely a tan\u00edt\u00f3 adatok alapj\u00e1n meghat\u00e1rozza a modell param\u00e9tereit.\n1\n\n\u2022 Adathalmaz:\n\u2013 Tan\u00edt\u00f3 p\u00e9ld\u00e1k: (x(i), y(i)), ahol i = 1, 2, . . . , m.\n\u2013 m: Tan\u00edt\u00f3 p\u00e9ld\u00e1k sz\u00e1ma.\n\u2013 x: Bemeneti v\u00e1ltoz\u00f3 (pl. h\u00e1z m\u00e9rete l\u00e1bban2).\n\u2013 y: Kimeneti v\u00e1ltoz\u00f3 (pl. h\u00e1z \u00e1ra ezer doll\u00e1rban).\n\u2022 P\u00e9lda adathalmaz (Portland, OR):\nH\u00e1z m\u00e9rete (x, l\u00e1bban2)\n\u00c1r (y, ezer doll\u00e1rban)\n2104\n460\n1416\n232\n1534\n315\n852\n178\n. . .\n. . .\n1. t\u00e1bl\u00e1zat. P\u00e9lda adathalmaz h\u00e1z\u00e1rak elrejelz\u00e9s\u00e9hez.\n\u2022 Jel\u00f6l\u00e9sek:\n\u2013 m: Tan\u00edt\u00f3 adatok sz\u00e1ma.\n\u2013 x: Bemeneti adat (jellemz, pl. h\u00e1z m\u00e9rete).\n\u2013 y: Kimeneti adat (c\u00e9lv\u00e1ltoz\u00f3, pl. h\u00e1z \u00e1ra).\n\u2022 Hipot\u00e9zis f\u00fcggv\u00e9ny:\nh\u03b8(x) = \u03b80 + \u03b81x\n\u2013 \u03b80: Tengelymetszet (bias), a f\u00fcggv\u00e9ny y-tengelyen val\u00f3 eltol\u00e1sa.\n\u2013 \u03b81: Meredeks\u00e9g (slope), amely a bemenet hat\u00e1s\u00e1t \u00edrja le az y-ra.\n\u2013 P\u00e9lda: Ha \u03b80 = 50, \u03b81 = 2, \u00e9s x = 100 (nm), akkor:\nh\u03b8(100) = 50 + 2 \u00b7 100 = 250 (ezer doll\u00e1r)\n\u2022 Tanul\u00f3 algoritmus: A c\u00e9l olyan \u03b80 \u00e9s \u03b81 param\u00e9terek megtal\u00e1l\u00e1sa, amelyekkel\nh\u03b8(x) a lehet legk\u00f6zelebb van az y-hoz minden tan\u00edt\u00f3 p\u00e9ld\u00e1ra. Ez egy optimaliz\u00e1ci\u00f3s\nprobl\u00e9ma, amelyet a k\u00f6lts\u00e9gf\u00fcggv\u00e9ny minimaliz\u00e1l\u00e1s\u00e1val oldunk meg.\n3. K\u00f6lts\u00e9gf\u00fcggv\u00e9ny\nA k\u00f6lts\u00e9gf\u00fcggv\u00e9ny (cost function) m\u00e9ri, hogy a hipot\u00e9zis f\u00fcggv\u00e9ny mennyire illeszkedik\naz adatokra, azaz mennyire pontosak az elrejelz\u00e9sek.\n\u2022 De\ufb01n\u00edci\u00f3:\nJ(\u03b80, \u03b81) =\n1\n2m\nm\n\u2211\ni=1\n(\nh\u03b8(x(i)) \u2212y(i))2\n2",
    "char_count": 1544,
    "token_estimate": 386
  },
  {
    "id": "doc-d4c67f4885a3-c0002",
    "index": 2,
    "text": "n\u00edt\u00f3 p\u00e9ld\u00e1ra. Ez egy optimaliz\u00e1ci\u00f3s\nprobl\u00e9ma, amelyet a k\u00f6lts\u00e9gf\u00fcggv\u00e9ny minimaliz\u00e1l\u00e1s\u00e1val oldunk meg.\n3. K\u00f6lts\u00e9gf\u00fcggv\u00e9ny\nA k\u00f6lts\u00e9gf\u00fcggv\u00e9ny (cost function) m\u00e9ri, hogy a hipot\u00e9zis f\u00fcggv\u00e9ny mennyire illeszkedik\naz adatokra, azaz mennyire pontosak az elrejelz\u00e9sek.\n\u2022 De\ufb01n\u00edci\u00f3:\nJ(\u03b80, \u03b81) =\n1\n2m\nm\n\u2211\ni=1\n(\nh\u03b8(x(i)) \u2212y(i))2\n2\n\n\u2013 N\u00e9gyzetes hiba:\n(\nh\u03b8(x(i)) \u2212y(i))2, amely az elrejelz\u00e9s \u00e9s a t\u00e9nyleges \u00e9rt\u00e9k k\u00f6-\nz\u00f6tti elt\u00e9r\u00e9st m\u00e9ri.\n\u2013 \u00c1tlagol\u00e1s:\n1\nm, hogy az adatpontok sz\u00e1m\u00e1t\u00f3l f\u00fcggetlen legyen.\n\u2013\n1\n2: Matematikai egyszers\u00edt\u00e9s a deriv\u00e1l\u00e1s sor\u00e1n.\n\u2022 Hipot\u00e9zis f\u00fcggv\u00e9ny:\nh\u03b8(x(i)) = \u03b80 + \u03b81x(i)\n\u2022 C\u00e9l: J(\u03b80, \u03b81) minimaliz\u00e1l\u00e1sa a legjobb \u03b80, \u03b81 \u00e9rt\u00e9kek megtal\u00e1l\u00e1s\u00e1val, hogy a modell\na lehet legpontosabb legyen.\n\u2022 P\u00e9lda sz\u00e1m\u00edt\u00e1s:\n\u2013 Adatok: (x(1), y(1)) = (1, 2), (x(2), y(2)) = (2, 4), m = 2.\n\u2013 Hipot\u00e9zis: h\u03b8(x) = 0 + 1 \u00b7 x.\n\u2013 Hib\u00e1k:\n\u2217h\u03b8(1) = 1, hiba: 1 \u22122 = \u22121, (1 \u22122)2 = 1.\n\u2217h\u03b8(2) = 2, hiba: 2 \u22124 = \u22122, (2 \u22124)2 = 4.\n\u2013 K\u00f6lts\u00e9g: J =\n1\n2\u00b72(1 + 4) = 1.25.\n4. K\u00f6lts\u00e9gf\u00fcggv\u00e9ny Vizualiz\u00e1ci\u00f3ja\nA k\u00f6lts\u00e9gf\u00fcggv\u00e9ny vizualiz\u00e1ci\u00f3ja seg\u00edt meg\u00e9rteni, hogyan v\u00e1ltozik a hiba a param\u00e9terek\nf\u00fcggv\u00e9ny\u00e9ben.\n\u2022 1D eset (\u03b80 = 0): J(\u03b81) egy parabola, amelynek minimuma a legjobb \u03b81 \u00e9rt\u00e9ket\nadja. Ez azt mutatja, hogy a meredeks\u00e9g (\u03b81) hogyan befoly\u00e1solja az illeszked\u00e9st.\n\u2022 2D eset (\u03b80, \u03b81): J(\u03b80, \u03b81) egy 3D t\u00e1l alak\u00fa fel\u00fclet, amely konvex, \u00edgy egyetlen\nglob\u00e1lis minimuma van.\n\u2022 Kont\u00far diagram: Ellipszisek mutatj\u00e1k az azonos J-\u00e9rt\u00e9keket, seg\u00edtve az optima-\nliz\u00e1ci\u00f3s folyamat szeml\u00e9ltet\u00e9s\u00e9t.\n\u2022 P\u00e9lda vizualiz\u00e1ci\u00f3: A diasor szerint, ha \u03b80 = \u22121, \u03b81 = 0, a modell nem illeszkedik\nj\u00f3l, m\u00edg \u03b80 = 0, \u03b81 = 0.5 jobb illeszked\u00e9st ad (l\u00e1sd a diasor 8. oldal\u00e1t).\n5. Gradiens Ereszked\u00e9s\nA gradiens ereszked\u00e9s (gradient descent) egy iterat\u00edv algoritmus, amely a k\u00f6lts\u00e9gf\u00fcggv\u00e9ny\n(J(\u03b80, \u03b81)) minimaliz\u00e1l\u00e1s\u00e1ra szolg\u00e1l az\u00e1ltal, hogy l\u00e9p\u00e9srl l\u00e9p\u00e9sre friss\u00edti a param\u00e9tereket.\n\u2022 Friss\u00edt\u00e9si szab\u00e1ly (j = 0, 1):\n\u03b8j := \u03b8j \u2212\u03b1 \u2202\n\u2202\u03b8j\nJ(\u03b80, \u03b81)\n3",
    "char_count": 1887,
    "token_estimate": 471
  },
  {
    "id": "doc-d4c67f4885a3-c0003",
    "index": 3,
    "text": "jobb illeszked\u00e9st ad (l\u00e1sd a diasor 8. oldal\u00e1t).\n5. Gradiens Ereszked\u00e9s\nA gradiens ereszked\u00e9s (gradient descent) egy iterat\u00edv algoritmus, amely a k\u00f6lts\u00e9gf\u00fcggv\u00e9ny\n(J(\u03b80, \u03b81)) minimaliz\u00e1l\u00e1s\u00e1ra szolg\u00e1l az\u00e1ltal, hogy l\u00e9p\u00e9srl l\u00e9p\u00e9sre friss\u00edti a param\u00e9tereket.\n\u2022 Friss\u00edt\u00e9si szab\u00e1ly (j = 0, 1):\n\u03b8j := \u03b8j \u2212\u03b1 \u2202\n\u2202\u03b8j\nJ(\u03b80, \u03b81)\n3\n\n\u2022 Parci\u00e1lis deriv\u00e1ltak:\n\u2202J\n\u2202\u03b80\n= 1\nm\nm\n\u2211\ni=1\n(\nh\u03b8(x(i)) \u2212y(i))\n\u2202J\n\u2202\u03b81\n= 1\nm\nm\n\u2211\ni=1\n(\nh\u03b8(x(i)) \u2212y(i))\n\u00b7 x(i)\n\u2022 Tanul\u00e1si r\u00e1ta (\u03b1): A l\u00e9p\u00e9sm\u00e9ret, amely meghat\u00e1rozza, hogy mekkora l\u00e9p\u00e9seket\ntesz az algoritmus a minimum fel\u00e9.\n\u2013 T\u00fal nagy \u03b1: Divergencia, az algoritmus t\u00fall\u00e9pheti a minimumot, vagy ak\u00e1r\ndiverg\u00e1lhat (l\u00e1sd a diasor 35. oldal\u00e1t).\n\u2013 T\u00fal kicsi \u03b1: Lass\u00fa konvergencia, ami idig\u00e9nyes lehet.\n\u2022 Algoritmus (egyidej friss\u00edt\u00e9s):\nism\u00e9teld, am\u00edg konverg\u00e1l\n\uf8f1\n\uf8f4\n\uf8f4\n\uf8f4\n\uf8f4\n\uf8f4\n\uf8f4\n\uf8f4\n\uf8f4\n\uf8f4\n\uf8f2\n\uf8f4\n\uf8f4\n\uf8f4\n\uf8f4\n\uf8f4\n\uf8f4\n\uf8f4\n\uf8f4\n\uf8f4\n\uf8f3\ntemp0 := \u03b80 \u2212\u03b1 1\nm\nm\n\u2211\ni=1\n(\nh\u03b8(x(i)) \u2212y(i))\ntemp1 := \u03b81 \u2212\u03b1 1\nm\nm\n\u2211\ni=1\n(\nh\u03b8(x(i)) \u2212y(i))\n\u00b7 x(i)\n\u03b80 := temp0\n\u03b81 := temp1\n\uf8fc\n\uf8f4\n\uf8f4\n\uf8f4\n\uf8f4\n\uf8f4\n\uf8f4\n\uf8f4\n\uf8f4\n\uf8f4\n\uf8fd\n\uf8f4\n\uf8f4\n\uf8f4\n\uf8f4\n\uf8f4\n\uf8f4\n\uf8f4\n\uf8f4\n\uf8f4\n\uf8fe\n\u2022 Konvergencia: A gradiens ereszked\u00e9s automatikusan kisebb l\u00e9p\u00e9seket tesz a mini-\nmum k\u00f6zel\u00e9ben, mivel a gradiens cs\u00f6kken, \u00edgy nincs sz\u00fcks\u00e9g \u03b1 idbeli cs\u00f6kkent\u00e9s\u00e9re\n(l\u00e1sd a diasor 37. oldal\u00e1t).\n\u2022 Batch Gradient Descent: A gradiens ereszked\u00e9s minden l\u00e9p\u00e9se az \u00f6sszes tan\u00edt\u00f3\nmint\u00e1t \ufb01gyelembe veszi (\u201ebatch\u201d), biztos\u00edtva a stabil konvergenci\u00e1t (l\u00e1sd a diasor\n54. oldal\u00e1t).\n6. Gyakorlati Szempontok\n\u2022 Jellemz sk\u00e1l\u00e1z\u00e1s: A bemeneteket (x) \u00e9rdemes sk\u00e1l\u00e1zni (pl. [0, 1] intervallumra) a\ngyorsabb konvergencia \u00e9rdek\u00e9ben, mivel ez cs\u00f6kkenti a k\u00f6lts\u00e9gf\u00fcggv\u00e9ny fel\u00fclet\u00e9nek\ntorzul\u00e1s\u00e1t.\n\u2022 Tanul\u00e1si r\u00e1ta: Pr\u00f3b\u00e1lj ki k\u00fcl\u00f6nb\u00f6z \u00e9rt\u00e9keket: \u03b1 = 0.001, 0.01, 0.1, \u00e9s \ufb01gyeld a\nkonvergencia viselked\u00e9s\u00e9t.\n\u2022 Konvergencia teszt: \u00c1br\u00e1zold J(\u03b80, \u03b81)-t az iter\u00e1ci\u00f3k f\u00fcggv\u00e9ny\u00e9ben, hogy ellen-\nrizd, cs\u00f6kken-e a k\u00f6lts\u00e9gf\u00fcggv\u00e9ny.\n\u2022 Hibakeres\u00e9s: Numerikus deriv\u00e1l\u00e1s haszn\u00e1lata a gradiensek ellenrz\u00e9s\u00e9re:\nJ(\u03b8j + \u03f5) \u2212J(\u03b8j \u2212\u03f5)\n2\u03f5\n4",
    "char_count": 1872,
    "token_estimate": 468
  },
  {
    "id": "doc-d4c67f4885a3-c0004",
    "index": 4,
    "text": "ul\u00e1si r\u00e1ta: Pr\u00f3b\u00e1lj ki k\u00fcl\u00f6nb\u00f6z \u00e9rt\u00e9keket: \u03b1 = 0.001, 0.01, 0.1, \u00e9s \ufb01gyeld a\nkonvergencia viselked\u00e9s\u00e9t.\n\u2022 Konvergencia teszt: \u00c1br\u00e1zold J(\u03b80, \u03b81)-t az iter\u00e1ci\u00f3k f\u00fcggv\u00e9ny\u00e9ben, hogy ellen-\nrizd, cs\u00f6kken-e a k\u00f6lts\u00e9gf\u00fcggv\u00e9ny.\n\u2022 Hibakeres\u00e9s: Numerikus deriv\u00e1l\u00e1s haszn\u00e1lata a gradiensek ellenrz\u00e9s\u00e9re:\nJ(\u03b8j + \u03f5) \u2212J(\u03b8j \u2212\u03f5)\n2\u03f5\n4\n\n\u2022 P\u00e9lda k\u00f3d (Python, a diasor \u00e9s PDF alapj\u00e1n):\nfor iter in range(max_iter):\npredictions = theta_0 + theta_1 * x\nerrors = predictions - y\ntheta_0 -= alpha * (1 / m) * sum(errors)\ntheta_1 -= alpha * (1 / m) * sum(errors * x)\nJ = (1 / (2 * m)) * sum(errors ** 2)\nif abs(J_old - J) < epsilon:\nbreak\n7. Alternat\u00edv Optimaliz\u00e1ci\u00f3\n\u2022 Norm\u00e1l egyenlet:\n\u03b8 =\n(\nXTX\n)\u22121 XTy\n\u2022 Elny: Nem iterat\u00edv, k\u00f6zvetlen megold\u00e1st ad, \u00edgy nincs sz\u00fcks\u00e9g tanul\u00e1si r\u00e1t\u00e1ra vagy\niter\u00e1ci\u00f3kra.\n\u2022 H\u00e1tr\u00e1ny: Lass\u00fa nagy m-re, mivel a m\u00e1trix inverzi\u00f3 sz\u00e1m\u00edt\u00e1si k\u00f6lts\u00e9ge jelents (pl.\nO(n3)).\n8. P\u00e9lda Alkalmaz\u00e1s\n\u2022 Probl\u00e9ma: H\u00e1z\u00e1rak elrejelz\u00e9se Portland, OR adathalmaz alapj\u00e1n.\n\u2022 Adatok: (100, 200), (150, 300), (200, 400).\n\u2022 Folyamat:\n1. Inicializ\u00e1l\u00e1s: \u03b80 = 0, \u03b81 = 0, \u03b1 = 0.01.\n2. Sk\u00e1l\u00e1z\u00e1s: x\u2032 = x\u2212100\n100 , hogy a bemenetek [0, 1]-re essenek.\n3. Gradiens ereszked\u00e9s futtat\u00e1sa az iterat\u00edv param\u00e9terfriss\u00edt\u00e9ssel.\n4. Eredm\u00e9ny: P\u00e9ld\u00e1ul h\u03b8(x) = 50 + 2x.\n\u2022 Predikci\u00f3: x = 175 nm:\nh\u03b8(175) = 50 + 2 \u00b7 175 = 400 (ezer doll\u00e1r)\n9. Kulcsformul\u00e1k\n\u2022 Hipot\u00e9zis:\nh\u03b8(x) = \u03b80 + \u03b81x\n\u2022 K\u00f6lts\u00e9gf\u00fcggv\u00e9ny:\nJ(\u03b80, \u03b81) =\n1\n2m\nm\n\u2211\ni=1\n(\nh\u03b8(x(i)) \u2212y(i))2\n5\n\n\u2022 Gradiens ereszked\u00e9s:\n\u03b80 := \u03b80 \u2212\u03b1 1\nm\nm\n\u2211\ni=1\n(\nh\u03b8(x(i)) \u2212y(i))\n\u03b81 := \u03b81 \u2212\u03b1 1\nm\nm\n\u2211\ni=1\n(\nh\u03b8(x(i)) \u2212y(i))\n\u00b7 x(i)\n10. A Kulcsformul\u00e1k K\u00f6z\u00f6tti K\u00fcl\u00f6nbs\u00e9g\n\u2022 Hipot\u00e9zis f\u00fcggv\u00e9ny (h\u03b8(x)): Ez a modell, amely elrejelzi a kimenetet (y) az adott\nbemenet (x) alapj\u00e1n, a param\u00e9terek (\u03b80 \u00e9s \u03b81) seg\u00edts\u00e9g\u00e9vel. Form\u00e1ja:\nh\u03b8(x(i)) = \u03b80 + \u03b81x(i)\n\u2022 K\u00f6lts\u00e9gf\u00fcggv\u00e9ny (J(\u03b80, \u03b81)): Ez a m\u00e9rsz\u00e1m, amely azt mutatja, hogy mennyire\nt\u00e9r el a hipot\u00e9zis a t\u00e9nyleges adatokt\u00f3l. A c\u00e9l a minimum\u00e1nak megtal\u00e1l\u00e1sa:\nJ(\u03b80, \u03b81) =\n1\n2m\nm\n\u2211\ni=1\n(\nh\u03b8(x(i)) \u2212y(i))2\n\u2022 Gradiens ereszked\u00e9s: Algoritmus a k\u00f6lts\u00e9gf\u00fcggv\u00e9ny minimaliz\u00e1l\u00e1s\u00e1ra az \u03b80 \u00e9s \u03b81\nparam\u00e9terek iterat\u00edv friss\u00edt\u00e9s\u00e9vel:\n\u03b80 := \u03b80 \u2212\u03b1 1\nm\nm\n\u2211\ni=1\n(\nh\u03b8(x(i)) \u2212y(i))\n\u03b81 := \u03b81 \u2212\u03b1 1\nm\nm\n\u2211\ni=1\n(\nh\u03b8(x(i)) \u2212y(i))\n\u00b7 x(i)\n6",
    "char_count": 2144,
    "token_estimate": 536
  }
]